cstest3/main3.py
cstest3-0.0.0.1.dist-info/METADATA
cstest3-0.0.0.1.dist-info/WHEEL
cstest3-0.0.0.1.dist-info/top_level.txt
cstest3-0.0.0.1.dist-info/RECORD
