Metadata-Version: 2.1
Name: cstest3
Version: 0.0.0.1
Summary: 연습문제5
Home-page: https://blog.naver.com/fpqaut
Author: Demeno
Author-email: fpqaut@naver.com
License: MIT
Platform: UNKNOWN
Requires-Python: >=3
